libbisca/__init__.py
libbisca/agent.py
libbisca/card.py
libbisca/state.py
tests/__init__.py
tests/unit/__init__.py
tests/unit/conftest.py
tests/unit/test_card.py
tests/unit/test_state.py
libbisca-0.1.2.dist-info/LICENSE.md
libbisca-0.1.2.dist-info/METADATA
libbisca-0.1.2.dist-info/WHEEL
libbisca-0.1.2.dist-info/top_level.txt
libbisca-0.1.2.dist-info/RECORD
