Metadata-Version: 2.1
Name: libbisca
Version: 0.1.2
Summary: A Python bisca library
Home-page: https://github.com/NunoMCSilva/libbisca
Author: Nuno Miguel Casteloa da Silva
Author-email: NunoMCSilva@gmail.com
License: GPL-3.0
Keywords: bisca,cards,card game
Platform: UNKNOWN
Classifier: Development Status :: 3 - Alpha
Classifier: Environment :: Console
Classifier: Intended Audience :: Developers
Classifier: License :: OSI Approved :: GNU General Public License v3 (GPLv3)
Classifier: Operating System :: OS Independent
Classifier: Programming Language :: Python :: 3.7
Classifier: Programming Language :: Python :: Implementation :: CPython
Classifier: Topic :: Games/Entertainment
Classifier: Topic :: Software Development :: Libraries :: Python Modules
Requires-Python: >=3.7
